mytestlib/__init__.py
mytestlib/greet.py
mytestlib/mytestlib/init__.py
mytestlib/mytestlib/src¥mytestlib¥greet.py
mytestlib_yuki-1.0.0.dist-info/METADATA
mytestlib_yuki-1.0.0.dist-info/WHEEL
mytestlib_yuki-1.0.0.dist-info/top_level.txt
mytestlib_yuki-1.0.0.dist-info/RECORD
