Metadata-Version: 2.4
Name: mytestlib-yuki
Version: 1.0.0
Summary: My Test Library.
Author-email: Yuki <yuki@sist.ac.jp>
License: lic
Project-URL: Homepage, http://www.sist.ac.jp
